koishi/__init__.py
koishi/contest.py
koishi/exceptions.py
koishi/models.py
koishi/problem.py
koishi/result.py
koishi/utils.py
koishi-1.1.6.dist-info/LICENSE
koishi-1.1.6.dist-info/METADATA
koishi-1.1.6.dist-info/WHEEL
koishi-1.1.6.dist-info/top_level.txt
koishi-1.1.6.dist-info/RECORD
