Metadata-Version: 2.1
Name: koishi
Version: 1.1.6
Summary: Python wrapper for the unofficial scraped API of the satori testing system.
Home-page: https://github.com/Cloud11665/koishi
Author: Cloud11665
Author-email: Cloud11665@gmail.com
License: MIT
Keywords: koishi,tcs,jagiellonian-university,satori
Platform: UNKNOWN
Classifier: License :: OSI Approved :: MIT License
Classifier: Programming Language :: Python :: 3
Classifier: Programming Language :: Python :: 3.8
Classifier: Programming Language :: Python :: 3.9
Classifier: Programming Language :: Python :: 3.10
Classifier: Operating System :: OS Independent
Requires-Python: >=3.8
Requires-Dist: beautifulsoup4 (==4.9.3)
Requires-Dist: certifi (==2020.12.5)
Requires-Dist: chardet (==4.0.0)
Requires-Dist: idna (==2.10)
Requires-Dist: lxml (==4.6.3)
Requires-Dist: markdownify (==0.6.5)
Requires-Dist: pydantic (==1.8.1)
Requires-Dist: requests (==2.25.1)
Requires-Dist: six (==1.15.0)
Requires-Dist: soupsieve (==2.2.1)
Requires-Dist: typing-extensions (==3.7.4.3)
Requires-Dist: urllib3 (==1.26.4)
